flxenv/__init__.py
flxenv/main.py
flxenv/version_manager.py
flxenv-1.1.dist-info/METADATA
flxenv-1.1.dist-info/WHEEL
flxenv-1.1.dist-info/entry_points.txt
flxenv-1.1.dist-info/top_level.txt
flxenv-1.1.dist-info/RECORD
