Metadata-Version: 2.1
Name: flxenv
Version: 1.1
Summary: Flux version manager
Home-page: https://github.com/nachrivcost/flxenv
Author: Jose Ignacio Rivero Costa
Author-email: joseignacio@riverocosta.com
Classifier: Development Status :: 3 - Alpha
Classifier: Intended Audience :: Developers
Classifier: License :: OSI Approved :: MIT License
Classifier: Programming Language :: Python :: 3.11
Requires-Dist: requests
